{
  "food_and_drinks": [
    { "word": "яблоко", "hint": "фрукт", "special": "груша" },
    { "word": "банан", "hint": "желтый", "special": "апельсин" },
    { "word": "пицца", "hint": "сыр", "special": "бургер" },
    { "word": "бургер", "hint": "мясо", "special": "сэндвич" },
    { "word": "картошка фри", "hint": "масло", "special": "чипсы" },
    { "word": "суп", "hint": "ложка", "special": "борщ" },
    { "word": "борщ", "hint": "красный", "special": "суп" },
    { "word": "чай", "hint": "чашка", "special": "кофе" },
    { "word": "кофе", "hint": "утро", "special": "чай" },
    { "word": "лимонад", "hint": "пузырьки", "special": "сок" },
    { "word": "сок", "hint": "фрукты", "special": "компот" },
    { "word": "компот", "hint": "ягоды", "special": "морс" },
    { "word": "мороженое", "hint": "холод", "special": "пломбир" },
    { "word": "шоколад", "hint": "сладость", "special": "конфета" },
    { "word": "конфета", "hint": "упаковка", "special": "шоколад" },
    { "word": "печенье", "hint": "крошки", "special": "пирожное" },
    { "word": "пирожное", "hint": "крем", "special": "торт" },
    { "word": "торт", "hint": "праздник", "special": "пирог" },
    { "word": "пирог", "hint": "выпечка", "special": "булочка" },
    { "word": "булочка", "hint": "тесто", "special": "батон" },
    { "word": "батон", "hint": "хлеб", "special": "багет" },
    { "word": "хлеб", "hint": "нарезка", "special": "батон" },
    { "word": "яйцо", "hint": "скорлупа", "special": "омлет" },
    { "word": "омлет", "hint": "завтрак", "special": "яйцо" },
    { "word": "сосиска", "hint": "мясо", "special": "колбаса" },
    { "word": "колбаса", "hint": "бутерброд", "special": "сосиска" },
    { "word": "сыр", "hint": "молоко", "special": "творог" },
    { "word": "творог", "hint": "белый", "special": "сыр" },
    { "word": "молоко", "hint": "коровка", "special": "кефир" },
    { "word": "кефир", "hint": "бутылка", "special": "йогурт" },
    { "word": "йогурт", "hint": "ложка", "special": "кефир" },
    { "word": "сметана", "hint": "густая", "special": "майонез" },
    { "word": "майонез", "hint": "соус", "special": "кетчуп" },
    { "word": "кетчуп", "hint": "томат", "special": "майонез" },
    { "word": "огурец", "hint": "зелёный", "special": "помидор" },
    { "word": "помидор", "hint": "красный", "special": "огурец" },
    { "word": "лук", "hint": "слёзы", "special": "чеснок" },
    { "word": "чеснок", "hint": "запах", "special": "лук" },
    { "word": "капуста", "hint": "листья", "special": "салат" },
    { "word": "салат", "hint": "овощи", "special": "капуста" },
    { "word": "виноград", "hint": "гроздь", "special": "ягоды" },
    { "word": "арбуз", "hint": "полоски", "special": "дыня" },
    { "word": "дыня", "hint": "сладкая", "special": "арбуз" },
    { "word": "апельсин", "hint": "цитрус", "special": "мандарины" },
    { "word": "мандарины", "hint": "новый год", "special": "апельсин" },
    { "word": "лимон", "hint": "кислый", "special": "лайм" },
    { "word": "лайм", "hint": "зелёный", "special": "лимон" },
    { "word": "вишня", "hint": "ягода", "special": "черешня" },
    { "word": "черешня", "hint": "лето", "special": "вишня" },
    { "word": "клубника", "hint": "ягода", "special": "малина" },
    { "word": "малина", "hint": "сладкая", "special": "клубника" },
    { "word": "голубика", "hint": "синяя", "special": "черника" },
    { "word": "черника", "hint": "ягоды", "special": "голубика" },
    { "word": "рис", "hint": "белый", "special": "гречка" },
    { "word": "гречка", "hint": "каша", "special": "рис" },
    { "word": "овсянка", "hint": "завтрак", "special": "каша" },
    { "word": "каша", "hint": "миска", "special": "овсянка" },
    { "word": "спагетти", "hint": "макароны", "special": "паста" },
    { "word": "паста", "hint": "итальянская", "special": "спагетти" },
    { "word": "суши", "hint": "япония", "special": "роллы" },
    { "word": "роллы", "hint": "рис", "special": "суши" },
    { "word": "пельмени", "hint": "тесто", "special": "вареники" },
    { "word": "вареники", "hint": "начинка", "special": "пельмени" },
    { "word": "котлета", "hint": "мясо", "special": "стейк" },
    { "word": "стейк", "hint": "гриль", "special": "котлета" },
    { "word": "курица", "hint": "мясо", "special": "индейка" },
    { "word": "индейка", "hint": "птица", "special": "курица" },
    { "word": "рыба", "hint": "вода", "special": "лосось" },
    { "word": "лосось", "hint": "красный", "special": "форель" },
    { "word": "форель", "hint": "река", "special": "лосось" },
    { "word": "краб", "hint": "панцирь", "special": "омар" },
    { "word": "омар", "hint": "морепродукт", "special": "краб" },
    { "word": "сырники", "hint": "творог", "special": "оладьи" },
    { "word": "оладьи", "hint": "жареные", "special": "блины" },
    { "word": "блины", "hint": "тонкие", "special": "оладьи" },
    { "word": "варенье", "hint": "ягоды", "special": "джем" },
    { "word": "джем", "hint": "сладкий", "special": "варенье" },
    { "word": "мёд", "hint": "пчёлы", "special": "сироп" },
    { "word": "сироп", "hint": "сладкий", "special": "мёд" },
    { "word": "соевый соус", "hint": "суши", "special": "кетчуп" },
    { "word": "томатный сок", "hint": "овощ", "special": "морковный сок" },
    { "word": "морковный сок", "hint": "оранжевый", "special": "яблочный сок" },
    { "word": "яблочный сок", "hint": "фрукт", "special": "грушевый сок" },
    { "word": "грушевый сок", "hint": "напиток", "special": "виноградный сок" },
    { "word": "виноградный сок", "hint": "фрукты", "special": "апельсиновый сок" },
    { "word": "молочный коктейль", "hint": "сладкий", "special": "смузи" },
    { "word": "смузи", "hint": "блендер", "special": "коктейль" },
    { "word": "газированная вода", "hint": "пузырьки", "special": "лимонад" },
    { "word": "минеральная вода", "hint": "бутылка", "special": "газированная вода" },
    { "word": "горячий шоколад", "hint": "зима", "special": "кофе" },
    { "word": "овощной суп", "hint": "ложка", "special": "томатный суп" },
    { "word": "томатный суп", "hint": "красный", "special": "овощной суп" },
    { "word": "куриный бульон", "hint": "тёплый", "special": "суп" },
    { "word": "жареная картошка", "hint": "сковорода", "special": "печёная картошка" },
    { "word": "печёная картошка", "hint": "духовка", "special": "жареная картошка" },
    { "word": "рис с овощами", "hint": "гарнир", "special": "гречка с мясом" },
    { "word": "гречка с мясом", "hint": "ужин", "special": "рис с овощами" }
  ],
  "animals_and_nature": [
    { "word": "кэлин", "hint": "харизма", "special": "еблан" },
    { "word": "никита", "hint": "очки", "special": "даун" },
    { "word": "максим", "hint": "ребенок", "special": "пацан" },
    { "word": "дану", "hint": "бмв", "special": "мужик" },
    { "word": "овидю", "hint": "девушка", "special": "уебок" },
    { "word": "чезар", "hint": "умный", "special": "король" },
    { "word": "кристи", "hint": "dhl", "special": "крутой пацан" },
    { "word": "бмв", "hint": "дану", "special": "мерседес" },
    { "word": "мерседес", "hint": "кэлин", "special": "бмв" },
    { "word": "роналду", "hint": "goat", "special": "месси" },
    { "word": "месси", "hint": "лох", "special": "роналду" },

    { "word": "кошка", "hint": "мяу", "special": "собака" },
    { "word": "собака", "hint": "гав", "special": "кошка" },
    { "word": "тигр", "hint": "полосы", "special": "лев" },
    { "word": "лев", "hint": "грива", "special": "тигр" },
    { "word": "заяц", "hint": "уши", "special": "кролик" },
    { "word": "кролик", "hint": "морковка", "special": "заяц" },
    { "word": "лиса", "hint": "рыжая", "special": "волк" },
    { "word": "волк", "hint": "вой", "special": "лиса" },
    { "word": "медведь", "hint": "берлога", "special": "гризли" },
    { "word": "ёж", "hint": "иголки", "special": "мышь" },
    { "word": "мышь", "hint": "сыр", "special": "крыса" },
    { "word": "крыса", "hint": "хвост", "special": "мышь" },
    { "word": "белка", "hint": "орех", "special": "ёж" },
    { "word": "олень", "hint": "рога", "special": "лось" },
    { "word": "лось", "hint": "лес", "special": "олень" },
    { "word": "енот", "hint": "полосы", "special": "лиса" },
    { "word": "хомяк", "hint": "щёки", "special": "мышь" },
    { "word": "свинья", "hint": "хрю", "special": "кабан" },
    { "word": "кабан", "hint": "лес", "special": "свинья" },
    { "word": "корова", "hint": "молоко", "special": "бык" },
    { "word": "бык", "hint": "рога", "special": "корова" },
    { "word": "овца", "hint": "шерсть", "special": "коза" },
    { "word": "коза", "hint": "рога", "special": "овца" },
    { "word": "лошадь", "hint": "грива", "special": "пони" },
    { "word": "пони", "hint": "маленькая", "special": "лошадь" },
    { "word": "осёл", "hint": "серый", "special": "лошадь" },
    { "word": "курица", "hint": "яйцо", "special": "петух" },
    { "word": "петух", "hint": "кукареку", "special": "курица" },
    { "word": "утка", "hint": "кря", "special": "гусь" },
    { "word": "гусь", "hint": "перья", "special": "утка" },
    { "word": "индейка", "hint": "праздник", "special": "курица" },
    { "word": "орёл", "hint": "высоко", "special": "ястреб" },
    { "word": "ястреб", "hint": "охота", "special": "орёл" },
    { "word": "сокол", "hint": "скорость", "special": "ястреб" },
    { "word": "воробей", "hint": "маленький", "special": "голубь" },
    { "word": "голубь", "hint": "письмо", "special": "воробей" },
    { "word": "ворона", "hint": "чёрная", "special": "грач" },
    { "word": "грач", "hint": "птица", "special": "ворона" },
    { "word": "пингвин", "hint": "холод", "special": "тюлень" },
    { "word": "тюлень", "hint": "морской", "special": "пингвин" },
    { "word": "дельфин", "hint": "умный", "special": "кит" },
    { "word": "кит", "hint": "огромный", "special": "дельфин" },
    { "word": "акула", "hint": "зубы", "special": "дельфин" },
    { "word": "осьминог", "hint": "щупальца", "special": "кальмар" },
    { "word": "кальмар", "hint": "море", "special": "осьминог" },
    { "word": "краб", "hint": "клешни", "special": "омар" },
    { "word": "омар", "hint": "панцирь", "special": "краб" },
    { "word": "рыба-клоун", "hint": "нимо", "special": "рыба" },
    { "word": "черепаха", "hint": "панцирь", "special": "улитка" },
    { "word": "улитка", "hint": "раковина", "special": "черепаха" },
    { "word": "лягушка", "hint": "ква", "special": "жаба" },
    { "word": "жаба", "hint": "озеро", "special": "лягушка" },
    { "word": "змея", "hint": "шип", "special": "уж" },
    { "word": "уж", "hint": "река", "special": "змея" },
    { "word": "крокодил", "hint": "река", "special": "аллигатор" },
    { "word": "аллигатор", "hint": "зубы", "special": "крокодил" },
    { "word": "пчела", "hint": "мёд", "special": "оса" },
    { "word": "оса", "hint": "жало", "special": "пчела" },
    { "word": "бабочка", "hint": "крылья", "special": "моль" },
    { "word": "моль", "hint": "одежда", "special": "бабочка" },
    { "word": "жук", "hint": "панцирь", "special": "кузнечик" },
    { "word": "кузнечик", "hint": "прыжок", "special": "саранча" },
    { "word": "саранча", "hint": "поле", "special": "кузнечик" },
    { "word": "муха", "hint": "жужжит", "special": "комар" },
    { "word": "комар", "hint": "укус", "special": "муха" },
    { "word": "паук", "hint": "сеть", "special": "скорпион" },
    { "word": "скорпион", "hint": "пустыня", "special": "паук" },
    { "word": "тигрёнок", "hint": "детёныш", "special": "львёнок" },
    { "word": "львёнок", "hint": "маленький", "special": "тигрёнок" },
    { "word": "медвежонок", "hint": "детёныш", "special": "щенок" },
    { "word": "щенок", "hint": "собака", "special": "котёнок" },
    { "word": "котёнок", "hint": "кошка", "special": "щенок" },
    { "word": "утёнок", "hint": "пруд", "special": "цыплёнок" },
    { "word": "цыплёнок", "hint": "желтый", "special": "утёнок" },
    { "word": "облако", "hint": "небо", "special": "туман" },
    { "word": "туман", "hint": "утро", "special": "облако" },
    { "word": "дождь", "hint": "капли", "special": "ливень" },
    { "word": "ливень", "hint": "гроза", "special": "дождь" },
    { "word": "снег", "hint": "зима", "special": "град" },
    { "word": "град", "hint": "камешки", "special": "снег" },
    { "word": "ветер", "hint": "дует", "special": "буря" },
    { "word": "буря", "hint": "сила", "special": "ветер" },
    { "word": "гроза", "hint": "молния", "special": "буря" },
    { "word": "молния", "hint": "небо", "special": "гром" },
    { "word": "гром", "hint": "звук", "special": "молния" },
    { "word": "солнце", "hint": "день", "special": "луна" },
    { "word": "луна", "hint": "ночь", "special": "солнце" },
    { "word": "звезда", "hint": "ночь", "special": "луна" },
    { "word": "гора", "hint": "высота", "special": "скала" },
    { "word": "скала", "hint": "камень", "special": "гора" },
    { "word": "река", "hint": "вода", "special": "ручей" },
    { "word": "ручей", "hint": "маленький", "special": "река" },
    { "word": "озеро", "hint": "вода", "special": "пруд" },
    { "word": "пруд", "hint": "лягушка", "special": "озеро" },
    { "word": "море", "hint": "волны", "special": "океан" },
    { "word": "океан", "hint": "большой", "special": "море" },
    { "word": "песок", "hint": "пляж", "special": "глина" },
    { "word": "камень", "hint": "тяжёлый", "special": "галька" },
    { "word": "трава", "hint": "зелёная", "special": "лист" },
    { "word": "лист", "hint": "дерево", "special": "трава" },
    { "word": "цветок", "hint": "пахнет", "special": "бутон" },
    { "word": "дерево", "hint": "ствол", "special": "куст" },
    { "word": "куст", "hint": "маленький", "special": "дерево" },
    { "word": "сад", "hint": "яблони", "special": "огород" },
    { "word": "огород", "hint": "овощи", "special": "сад" }
  ],
  "people_and_jobs": [
    { "word": "врач", "hint": "больница", "special": "медсестра" },
    { "word": "учитель", "hint": "школа", "special": "преподаватель" },
    { "word": "повар", "hint": "кухня", "special": "кондитер" },
    { "word": "полицейский", "hint": "закон", "special": "охранник" },
    { "word": "пожарный", "hint": "пламя", "special": "спасатель" },
    { "word": "солдат", "hint": "армия", "special": "военный" },
    { "word": "строитель", "hint": "дом", "special": "рабочий" },
    { "word": "водитель автобуса", "hint": "транспорт", "special": "таксист" },
    { "word": "таксист", "hint": "машина", "special": "водитель автобуса" },
    { "word": "пекарь", "hint": "хлеб", "special": "кондитер" },
    { "word": "кондитер", "hint": "сладости", "special": "пекарь" },
    { "word": "фотограф", "hint": "камера", "special": "оператор" },
    { "word": "оператор", "hint": "съёмка", "special": "фотограф" },
    { "word": "певец", "hint": "песня", "special": "музыкант" },
    { "word": "музыкант", "hint": "инструмент", "special": "певец" },
    { "word": "актёр", "hint": "сцена", "special": "режиссёр" },
    { "word": "режиссёр", "hint": "кино", "special": "актёр" },
    { "word": "дизайнер", "hint": "креатив", "special": "архитектор" },
    { "word": "архитектор", "hint": "план", "special": "дизайнер" },
    { "word": "пилот", "hint": "самолёт", "special": "космонавт" },
    { "word": "космонавт", "hint": "космос", "special": "пилот" },
    { "word": "моряк", "hint": "корабль", "special": "рыбак" },
    { "word": "рыбак", "hint": "удочка", "special": "моряк" },
    { "word": "журналист", "hint": "новости", "special": "редактор" },
    { "word": "редактор", "hint": "текст", "special": "журналист" },
    { "word": "библиотекарь", "hint": "книги", "special": "архивариус" },
    { "word": "архивариус", "hint": "документы", "special": "библиотекарь" },
    { "word": "учёный", "hint": "эксперимент", "special": "исследователь" },
    { "word": "исследователь", "hint": "открытие", "special": "учёный" },
    { "word": "инженер", "hint": "техника", "special": "конструктор" },
    { "word": "конструктор", "hint": "проект", "special": "инженер" },
    { "word": "программист", "hint": "код", "special": "разработчик" },
    { "word": "разработчик", "hint": "софт", "special": "программист" },
    { "word": "воспитатель", "hint": "дети", "special": "няня" },
    { "word": "няня", "hint": "уход", "special": "воспитатель" },
    { "word": "парикмахер", "hint": "волосы", "special": "стилист" },
    { "word": "стилист", "hint": "образ", "special": "парикмахер" },
    { "word": "маникюрист", "hint": "ногти", "special": "педикюрист" },
    { "word": "педикюрист", "hint": "ноги", "special": "маникюрист" },
    { "word": "спортсмен", "hint": "тренировка", "special": "атлет" },
    { "word": "атлет", "hint": "соревнование", "special": "спортсмен" },
    { "word": "тренер", "hint": "команда", "special": "инструктор" },
    { "word": "инструктор", "hint": "обучение", "special": "тренер" },
    { "word": "художник", "hint": "краски", "special": "скульптор" },
    { "word": "скульптор", "hint": "камень", "special": "художник" },
    { "word": "плотник", "hint": "дерево", "special": "столяр" },
    { "word": "столяр", "hint": "инструмент", "special": "плотник" },
    { "word": "слесарь", "hint": "металл", "special": "механик" },
    { "word": "механик", "hint": "машина", "special": "слесарь" },
    { "word": "электрик", "hint": "провод", "special": "техник" },
    { "word": "техник", "hint": "оборудование", "special": "электрик" },
    { "word": "сантехник", "hint": "трубы", "special": "водопроводчик" },
    { "word": "водопроводчик", "hint": "вода", "special": "сантехник" },
    { "word": "пилот вертолёта", "hint": "высота", "special": "пилот" },
    { "word": "грузчик", "hint": "поднять", "special": "разгрузчик" },
    { "word": "разгрузчик", "hint": "ящики", "special": "грузчик" },
    { "word": "курьер", "hint": "доставка", "special": "почтальон" },
    { "word": "почтальон", "hint": "письмо", "special": "курьер" },
    { "word": "бухгалтер", "hint": "цифры", "special": "экономист" },
    { "word": "экономист", "hint": "финансы", "special": "бухгалтер" },
    { "word": "юрист", "hint": "закон", "special": "адвокат" },
    { "word": "адвокат", "hint": "суд", "special": "юрист" },
    { "word": "судья", "hint": "решение", "special": "присяжный" },
    { "word": "присяжный", "hint": "суд", "special": "судья" },
    { "word": "депутат", "hint": "закон", "special": "сенатор" },
    { "word": "сенатор", "hint": "парламент", "special": "депутат" },
    { "word": "мэр", "hint": "город", "special": "губернатор" },
    { "word": "губернатор", "hint": "область", "special": "мэр" },
    { "word": "президент", "hint": "страна", "special": "канцлер" },
    { "word": "канцлер", "hint": "правительство", "special": "президент" },
    { "word": "певица", "hint": "песня", "special": "певец" },
    { "word": "балерина", "hint": "танец", "special": "хореограф" },
    { "word": "хореограф", "hint": "постановка", "special": "балерина" },
    { "word": "дрессировщик", "hint": "животные", "special": "кинолог" },
    { "word": "кинолог", "hint": "собаки", "special": "дрессировщик" },
    { "word": "садовник", "hint": "цветы", "special": "фермер" },
    { "word": "фермер", "hint": "урожай", "special": "садовник" },
    { "word": "повар кондитер", "hint": "торты", "special": "шоколатье" },
    { "word": "шоколатье", "hint": "шоколад", "special": "повар кондитер" },
    { "word": "таксист-дальнобойщик", "hint": "дальние поездки", "special": "водитель автобуса" },
    { "word": "стюардесса", "hint": "самолёт", "special": "пилот" },
    { "word": "учёный-биолог", "hint": "эксперимент", "special": "исследователь" },
    { "word": "инженер-механик", "hint": "механизмы", "special": "инженер" },
    { "word": "программист-разработчик", "hint": "код", "special": "разработчик" },
    { "word": "разработчик софта", "hint": "приложение", "special": "программист" },
    { "word": "оператор кино", "hint": "камера", "special": "фотограф" },
    { "word": "оператор телевидения", "hint": "экран", "special": "оператор кино" },
    { "word": "доктор наук", "hint": "учёный", "special": "исследователь" },
    { "word": "исследователь природы", "hint": "лес", "special": "учёный" },
    { "word": "строитель мостов", "hint": "река", "special": "инженер" },
    { "word": "инженер-строитель", "hint": "дом", "special": "конструктор" },
    { "word": "учитель музыки", "hint": "инструмент", "special": "педагог" },
    { "word": "учитель рисования", "hint": "краски", "special": "педагог" },
    { "word": "медсестра", "hint": "уход", "special": "врач" },
    { "word": "фармацевт", "hint": "лекарство", "special": "аптекарь" },
    { "word": "аптекарь", "hint": "таблетки", "special": "фармацевт" },
    { "word": "инструктор по йоге", "hint": "поза", "special": "тренер" },
    { "word": "тренер по фитнесу", "hint": "тренировка", "special": "инструктор по йоге" },
    { "word": "балетмейстер", "hint": "танец", "special": "хореограф" },
    { "word": "директор школы", "hint": "администрация", "special": "директор университета" },
    { "word": "директор университета", "hint": "ректор", "special": "директор школы" },
    { "word": "психолог", "hint": "эмоции", "special": "психиатр" },
    { "word": "психиатр", "hint": "лечение", "special": "психолог" },
    { "word": "детектив", "hint": "расследование", "special": "сыщик" },
    { "word": "сыщик", "hint": "тайна", "special": "детектив" },
    { "word": "гид", "hint": "экскурсия", "special": "путеводитель" },
    { "word": "путеводитель", "hint": "город", "special": "гид" },
    { "word": "дизайнер интерьера", "hint": "комната", "special": "архитектор" },
    { "word": "архитектор интерьера", "hint": "проект", "special": "дизайнер интерьера" },
    { "word": "дирижёр оркестра", "hint": "музыка", "special": "певец" },
    { "word": "организатор мероприятий", "hint": "событие", "special": "координатор" },
    { "word": "координатор проектов", "hint": "план", "special": "организатор мероприятий" },
    { "word": "эколог", "hint": "природа", "special": "биолог" },
    { "word": "биолог", "hint": "животные", "special": "эколог" },
    { "word": "геолог", "hint": "камни", "special": "археолог" },
    { "word": "археолог", "hint": "раскопки", "special": "геолог" }
  ],
  "home_and_objects": [
    { "word": "стол", "hint": "есть", "special": "комод" },
    { "word": "стул", "hint": "сидеть", "special": "кресло" },
    { "word": "кресло", "hint": "удобно", "special": "диван" },
    { "word": "диван", "hint": "отдых", "special": "кресло" },
    { "word": "кровать", "hint": "сон", "special": "раскладушка" },
    { "word": "раскладушка", "hint": "спать", "special": "кровать" },
    { "word": "шкаф", "hint": "одежда", "special": "комод" },
    { "word": "комод", "hint": "ящики", "special": "шкаф" },
    { "word": "полка", "hint": "книги", "special": "стеллаж" },
    { "word": "стеллаж", "hint": "хранение", "special": "полка" },
    { "word": "лампа", "hint": "свет", "special": "торшер" },
    { "word": "торшер", "hint": "угол", "special": "лампа" },
    { "word": "картинка", "hint": "стена", "special": "плакат" },
    { "word": "плакат", "hint": "декор", "special": "картина" },
    { "word": "ковёр", "hint": "пол", "special": "палас" },
    { "word": "палас", "hint": "комната", "special": "ковёр" },
    { "word": "занавеска", "hint": "окно", "special": "штора" },
    { "word": "штора", "hint": "закрыть", "special": "занавеска" },
    { "word": "подушка", "hint": "голова", "special": "валик" },
    { "word": "валик", "hint": "сон", "special": "подушка" },
    { "word": "одеяло", "hint": "тёпло", "special": "плед" },
    { "word": "плед", "hint": "мягко", "special": "одеяло" },
    { "word": "коврик", "hint": "вход", "special": "дорожка" },
    { "word": "дорожка", "hint": "пол", "special": "коврик" },
    { "word": "часы", "hint": "время", "special": "будильник" },
    { "word": "будильник", "hint": "звон", "special": "часы" },
    { "word": "зеркало", "hint": "отражение", "special": "стекло" },
    { "word": "стекло", "hint": "прозрачное", "special": "зеркало" },
    { "word": "картина", "hint": "декор", "special": "плакат" },
    { "word": "дверь", "hint": "открыть", "special": "ворота" },
    { "word": "ворота", "hint": "вход", "special": "дверь" },
    { "word": "окно", "hint": "свет", "special": "форточка" },
    { "word": "форточка", "hint": "вентиляция", "special": "окно" },
    { "word": "телевизор", "hint": "смотреть", "special": "монитор" },
    { "word": "монитор", "hint": "экран", "special": "телевизор" },
    { "word": "радио", "hint": "музыка", "special": "колонки" },
    { "word": "колонки", "hint": "звук", "special": "радио" },
    { "word": "холодильник", "hint": "еда", "special": "морозильник" },
    { "word": "морозильник", "hint": "заморозка", "special": "холодильник" },
    { "word": "плита", "hint": "готовка", "special": "духовка" },
    { "word": "духовка", "hint": "выпекать", "special": "плита" },
    { "word": "микроволновка", "hint": "разогрев", "special": "печь" },
    { "word": "печь", "hint": "тепло", "special": "микроволновка" },
    { "word": "стиральная машина", "hint": "одежда", "special": "сушилка" },
    { "word": "сушилка", "hint": "сушка", "special": "стиральная машина" },
    { "word": "пылесос", "hint": "уборка", "special": "швабра" },
    { "word": "швабра", "hint": "пол", "special": "пылесос" },
    { "word": "утюг", "hint": "гладить", "special": "парогенератор" },
    { "word": "парогенератор", "hint": "пар", "special": "утюг" },
    { "word": "чайник", "hint": "вода", "special": "термопот" },
    { "word": "термопот", "hint": "вода", "special": "чайник" },
    { "word": "кастрюля", "hint": "готовка", "special": "сковорода" },
    { "word": "сковорода", "hint": "жарка", "special": "кастрюля" },
    { "word": "нож", "hint": "резать", "special": "топор" },
    { "word": "вилка", "hint": "есть", "special": "ложка" },
    { "word": "ложка", "hint": "суп", "special": "вилка" },
    { "word": "тарелка", "hint": "еда", "special": "миска" },
    { "word": "миска", "hint": "суп", "special": "тарелка" },
    { "word": "чашка", "hint": "чай", "special": "стакан" },
    { "word": "стакан", "hint": "вода", "special": "чашка" },
    { "word": "бутылка", "hint": "жидкость", "special": "банка" },
    { "word": "банка", "hint": "консервы", "special": "бутылка" },
    { "word": "ковш", "hint": "вода", "special": "черпак" },
    { "word": "черпак", "hint": "суп", "special": "ковш" },
    { "word": "корзина", "hint": "вещи", "special": "ящик" },
    { "word": "ящик", "hint": "хранение", "special": "корзина" },
    { "word": "сундук", "hint": "сокровища", "special": "ящик" },
    { "word": "книга", "hint": "читать", "special": "журнал" },
    { "word": "журнал", "hint": "статьи", "special": "книга" },
    { "word": "газета", "hint": "новости", "special": "журнал" },
    { "word": "лампочка", "hint": "свет", "special": "светильник" },
    { "word": "светильник", "hint": "лампа", "special": "лампочка" },
    { "word": "вешалка", "hint": "одежда", "special": "крючок" },
    { "word": "крючок", "hint": "повесить", "special": "вешалка" },
    { "word": "карман", "hint": "одежда", "special": "сумка" },
    { "word": "сумка", "hint": "носить", "special": "карман" },
    { "word": "коврик для ванной", "hint": "вода", "special": "полотенце" },
    { "word": "полотенце", "hint": "влажное", "special": "коврик для ванной" },
    { "word": "мусорное ведро", "hint": "мусор", "special": "корзина" },
    { "word": "зонтик", "hint": "дождь", "special": "плащ" },
    { "word": "плащ", "hint": "дождь", "special": "зонтик" },
    { "word": "коврик для двери", "hint": "вытирать", "special": "дорожка" },
    { "word": "дорожка", "hint": "пол", "special": "коврик для двери" },
    { "word": "ручка двери", "hint": "открыть", "special": "замок" },
    { "word": "замок", "hint": "закрыть", "special": "ручка двери" },
    { "word": "подставка для обуви", "hint": "туфли", "special": "полка" },
    { "word": "корзина для белья", "hint": "стирка", "special": "ящик" },
    { "word": "светильник настольный", "hint": "рабочий", "special": "лампа" },
    { "word": "ковёр в гостиную", "hint": "пол", "special": "палас" },
    { "word": "шкаф для обуви", "hint": "туфли", "special": "полка" },
    { "word": "подоконник", "hint": "цветы", "special": "полка" },
    { "word": "декоративная ваза", "hint": "цветы", "special": "бутылка" },
    { "word": "настенные часы", "hint": "время", "special": "будильник" },
    { "word": "полка для книг", "hint": "книги", "special": "стеллаж" },
    { "word": "комод в спальне", "hint": "одежда", "special": "шкаф" },
    { "word": "кровать двухспальная", "hint": "сон", "special": "диван" },
    { "word": "тумбочка", "hint": "ночь", "special": "комод" },
    { "word": "шкаф для посуды", "hint": "тарелки", "special": "полка" },
    { "word": "барная стойка", "hint": "кухня", "special": "стол" },
    { "word": "кухонный стол", "hint": "есть", "special": "барная стойка" },
    { "word": "барная мебель", "hint": "кухня", "special": "стол" },
    { "word": "шкаф-купе", "hint": "одежда", "special": "комод" }
  ],
  "transport_and_places": [
    { "word": "автобус", "hint": "остановка", "special": "маршрутка" },
    { "word": "маршрутка", "hint": "дорога", "special": "автобус" },
    { "word": "поезд", "hint": "рельсы", "special": "метро" },
    { "word": "метро", "hint": "подземка", "special": "поезд" },
    { "word": "такси", "hint": "машина", "special": "автомобиль" },
    { "word": "самолёт", "hint": "небо", "special": "вертолёт" },
    { "word": "вертолёт", "hint": "крутить", "special": "самолёт" },
    { "word": "корабль", "hint": "вода", "special": "яхта" },
    { "word": "яхта", "hint": "парус", "special": "корабль" },
    { "word": "велосипед", "hint": "педали", "special": "самокат" },
    { "word": "самокат", "hint": "кататься", "special": "велосипед" },
    { "word": "мотоцикл", "hint": "скорость", "special": "скутер" },
    { "word": "скутер", "hint": "город", "special": "мотоцикл" },
    { "word": "машина", "hint": "дорога", "special": "автомобиль" },
    { "word": "грузовик", "hint": "транспорт", "special": "фургон" },
    { "word": "фургон", "hint": "груз", "special": "грузовик" },
    { "word": "трамвай", "hint": "рельсы", "special": "метро" },
    { "word": "метро поезд", "hint": "подземка", "special": "трамвай" },
    { "word": "автодорога", "hint": "машины", "special": "шоссе" },
    { "word": "шоссе", "hint": "дорога", "special": "автодорога" },
    { "word": "пешеходная дорожка", "hint": "идти", "special": "тропинка" },
    { "word": "тропинка", "hint": "лес", "special": "пешеходная дорожка" },
    { "word": "аэропорт", "hint": "самолёт", "special": "вокзал" },
    { "word": "вокзал", "hint": "поезд", "special": "аэропорт" },
    { "word": "станция метро", "hint": "поезд", "special": "вокзал" },
    { "word": "остановка автобуса", "hint": "ждать", "special": "станция" },
    { "word": "порт", "hint": "корабль", "special": "гавань" },
    { "word": "гавань", "hint": "лодки", "special": "порт" },
    { "word": "городской парк", "hint": "отдых", "special": "сад" },
    { "word": "сад", "hint": "цветы", "special": "городской парк" },
    { "word": "площадь", "hint": "центр", "special": "сквер" },
    { "word": "сквер", "hint": "зелень", "special": "площадь" },
    { "word": "улица", "hint": "дома", "special": "проспект" },
    { "word": "проспект", "hint": "дорога", "special": "улица" },
    { "word": "перекрёсток", "hint": "дорога", "special": "тупик" },
    { "word": "тупик", "hint": "конец", "special": "перекрёсток" },
    { "word": "мост", "hint": "река", "special": "плотина" },
    { "word": "плотина", "hint": "вода", "special": "мост" },
    { "word": "туннель", "hint": "подземка", "special": "мост" },
    { "word": "пешеходный мост", "hint": "идти", "special": "туннель" },
    { "word": "торговый центр", "hint": "магазины", "special": "рынок" },
    { "word": "рынок", "hint": "товары", "special": "торговый центр" },
    { "word": "супермаркет", "hint": "еда", "special": "магазин" },
    { "word": "магазин одежды", "hint": "шопинг", "special": "бутик" },
    { "word": "бутик", "hint": "стиль", "special": "магазин одежды" },
    { "word": "кафе", "hint": "еда", "special": "ресторан" },
    { "word": "ресторан", "hint": "питание", "special": "кафе" },
    { "word": "кинотеатр", "hint": "фильм", "special": "театр" },
    { "word": "театр", "hint": "сцена", "special": "кинотеатр" },
    { "word": "музей", "hint": "картины", "special": "выставка" },
    { "word": "выставка", "hint": "артефакты", "special": "музей" },
    { "word": "библиотека", "hint": "книги", "special": "читалня" },
    { "word": "читалня", "hint": "учёба", "special": "библиотека" },
    { "word": "школа", "hint": "учёба", "special": "университет" },
    { "word": "университет", "hint": "студенты", "special": "школа" },
    { "word": "детский сад", "hint": "дети", "special": "ясли" },
    { "word": "ясли", "hint": "малыши", "special": "детский сад" },
    { "word": "больница", "hint": "врач", "special": "поликлиника" },
    { "word": "поликлиника", "hint": "лечение", "special": "больница" },
    { "word": "аптека", "hint": "лекарства", "special": "магазин здоровья" },
    { "word": "магазин здоровья", "hint": "витамины", "special": "аптека" },
    { "word": "станция техобслуживания", "hint": "ремонт", "special": "гараж" },
    { "word": "гараж", "hint": "машина", "special": "станция техобслуживания" },
    { "word": "автозаправка", "hint": "бензин", "special": "АЗС" },
    { "word": "АЗС", "hint": "топливо", "special": "автозаправка" },
    { "word": "остров", "hint": "вода", "special": "мыс" },
    { "word": "мыс", "hint": "берег", "special": "остров" },
    { "word": "пляж", "hint": "песок", "special": "берег" },
    { "word": "берег реки", "hint": "вода", "special": "пляж" },
    { "word": "гора", "hint": "высота", "special": "холм" },
    { "word": "холм", "hint": "небольшой", "special": "гора" },
    { "word": "лес", "hint": "деревья", "special": "парк" },
    { "word": "парк лесной", "hint": "прогулка", "special": "лес" },
    { "word": "площадка для игр", "hint": "дети", "special": "спортплощадка" },
    { "word": "спортплощадка", "hint": "спорт", "special": "площадка для игр" },
    { "word": "стадион", "hint": "спорт", "special": "арена" },
    { "word": "арена", "hint": "событие", "special": "стадион" },
    { "word": "пешеходная зона", "hint": "идти", "special": "улица" },
    { "word": "торговая улица", "hint": "магазины", "special": "пешеходная зона" },
    { "word": "площадь города", "hint": "центр", "special": "сквер" },
    { "word": "сквер города", "hint": "зелень", "special": "площадь города" },
    { "word": "обсерватория", "hint": "звёзды", "special": "планетарий" },
    { "word": "планетарий", "hint": "космос", "special": "обсерватория" },
    { "word": "аквапарк", "hint": "вода", "special": "бассейн" },
    { "word": "бассейн", "hint": "плавать", "special": "аквапарк" },
    { "word": "зоопарк", "hint": "животные", "special": "питомник" },
    { "word": "питомник", "hint": "животные", "special": "зоопарк" },
    { "word": "кафедральный собор", "hint": "церковь", "special": "храм" },
    { "word": "храм", "hint": "религия", "special": "кафедральный собор" }
  ],
   "fun_and_games": [
    { "word": "шарики для игры", "hint": "катать", "special": "петанк" },
    { "word": "пазл", "hint": "собирать", "special": "мозаика" },
    { "word": "мозаика", "hint": "детали", "special": "пазл" },
    { "word": "конструктор", "hint": "строить", "special": "лего" },
    { "word": "лего", "hint": "кубики", "special": "конструктор" },
    { "word": "настольная игра", "hint": "доска", "special": "карточная игра" },
    { "word": "карточная игра", "hint": "карты", "special": "настольная игра" },
    { "word": "кубики", "hint": "строить", "special": "лего" },
    { "word": "мяч футбольный", "hint": "гол", "special": "мяч волейбольный" },
    { "word": "мяч волейбольный", "hint": "сетка", "special": "мяч футбольный" },
    { "word": "мяч баскетбольный", "hint": "кольцо", "special": "мяч волейбольный" },
    { "word": "скейтборд", "hint": "кататься", "special": "ролики" },
    { "word": "ролики", "hint": "скорость", "special": "скейтборд" },
    { "word": "самокат детский", "hint": "движение", "special": "велосипед" },
    { "word": "велосипед детский", "hint": "педали", "special": "самокат" },
    { "word": "батут", "hint": "прыжки", "special": "качели" },
    { "word": "качели", "hint": "летать", "special": "батут" },
    { "word": "горка детская", "hint": "скат", "special": "песочница" },
    { "word": "песочница", "hint": "песок", "special": "горка детская" },
    { "word": "мини-гольф", "hint": "клюшка", "special": "гольф" },
    { "word": "гольф", "hint": "поле", "special": "мини-гольф" },
    { "word": "боулинг", "hint": "шар", "special": "кегли" },
    { "word": "кегли", "hint": "сбивать", "special": "боулинг" },
    { "word": "настольный теннис", "hint": "ракетка", "special": "пинг-понг" },
    { "word": "пинг-понг", "hint": "мяч", "special": "настольный теннис" },
    { "word": "шахматы", "hint": "король", "special": "шашки" },
    { "word": "шашки", "hint": "фигуры", "special": "шахматы" },
    { "word": "домино", "hint": "плитки", "special": "карточная игра" },
    { "word": "игрушечный поезд", "hint": "рельсы", "special": "машинка" },
    { "word": "машинка игрушечная", "hint": "колёса", "special": "игрушечный поезд" },
    { "word": "кукла", "hint": "одежда", "special": "мягкая игрушка" },
    { "word": "мягкая игрушка", "hint": "плюш", "special": "кукла" },
    { "word": "песочные часы", "hint": "время", "special": "таймер" },
    { "word": "таймер", "hint": "секунды", "special": "песочные часы" },
    { "word": "карточки для игры", "hint": "играть", "special": "фишки" },
    { "word": "фишки", "hint": "ставки", "special": "карточки для игры" },
    { "word": "сабле", "hint": "меч", "special": "рапира" },
    { "word": "рапира", "hint": "шпага", "special": "сабле" },
    { "word": "обручи", "hint": "крутить", "special": "скакалка" },
    { "word": "скакалка", "hint": "прыжки", "special": "обручи" },
    { "word": "спортивный мяч", "hint": "игра", "special": "мяч детский" },
    { "word": "велотренажёр", "hint": "крутить", "special": "беговая дорожка" },
    { "word": "беговая дорожка", "hint": "ходьба", "special": "велотренажёр" },
    { "word": "бильярд", "hint": "шары", "special": "пул" },
    { "word": "пул", "hint": "бильярд", "special": "бильярд" },
    { "word": "дартс", "hint": "меткость", "special": "лук и стрелы" },
    { "word": "лук и стрелы", "hint": "цель", "special": "дартс" },
    { "word": "игровой планшет", "hint": "сенсор", "special": "консоль" },
    { "word": "консоль игровая", "hint": "кнопки", "special": "игровой планшет" },
    { "word": "плейстейшн", "hint": "игры", "special": "ксбокс" },
    { "word": "ксбокс", "hint": "игры", "special": "плейстейшн" },
    { "word": "карточная колода", "hint": "играть", "special": "фишки" },
    { "word": "настольная ферма", "hint": "животные", "special": "лотерея" },
    { "word": "лотерея", "hint": "билет", "special": "настольная ферма" },
    { "word": "снежки", "hint": "играть", "special": "лед" },
    { "word": "ледянки", "hint": "кататься", "special": "снежки" },
    { "word": "снежная крепость", "hint": "зима", "special": "снежная баба" },
    { "word": "снежная баба", "hint": "зима", "special": "снежная крепость" },
    { "word": "водяной пистолет", "hint": "вода", "special": "брызгалка" },
    { "word": "брызгалка", "hint": "игра", "special": "водяной пистолет" },
    { "word": "мыльные пузыри", "hint": "летать", "special": "шарики" },
    { "word": "шарики", "hint": "кататься", "special": "мыльные пузыри" },
    { "word": "петанк", "hint": "шарики", "special": "боулинг" },
    { "word": "мини-футбол", "hint": "ворота", "special": "футбол" },
    { "word": "футбол", "hint": "мяч", "special": "мини-футбол" },
    { "word": "волейбол", "hint": "сетка", "special": "бейсбол" },
    { "word": "бейсбол", "hint": "битка", "special": "волейбол" },
    { "word": "теннис", "hint": "ракетка", "special": "настольный теннис" },
    { "word": "пинг-понг детский", "hint": "мячик", "special": "настольный теннис" },
    { "word": "городки", "hint": "меткость", "special": "кегли" },
    { "word": "классики", "hint": "прыжки", "special": "скакалка" },
    { "word": "снежные гонки", "hint": "зима", "special": "катание на санках" },
    { "word": "катание на санках", "hint": "скат", "special": "снежные гонки" },
    { "word": "катание на лыжах", "hint": "снег", "special": "сноуборд" },
    { "word": "сноуборд", "hint": "склон", "special": "катание на лыжах" },
    { "word": "пинг-понг на улице", "hint": "мяч", "special": "настольный теннис" },
    { "word": "гонки на велосипедах", "hint": "скорость", "special": "гонки на самокатах" },
    { "word": "гонки на самокатах", "hint": "скорость", "special": "гонки на велосипедах" },
    { "word": "картинг", "hint": "машины", "special": "гонки на велосипедах" },
    { "word": "лазертаг", "hint": "стрельба", "special": "пейнтбол" },
    { "word": "пейнтбол", "hint": "краска", "special": "лазертаг" },
    { "word": "боулинг детский", "hint": "шар", "special": "кегли" },
    { "word": "мини-бильярд", "hint": "шары", "special": "бильярд" },
    { "word": "мини-гольф детский", "hint": "клюшка", "special": "гольф" },
    { "word": "игровой автомат", "hint": "кнопки", "special": "консоль" },
    { "word": "дженга", "hint": "строить", "special": "блоки" },
    { "word": "блоки", "hint": "кубики", "special": "дженга" },
    { "word": "настольная ферма детская", "hint": "животные", "special": "лотерея" },
    { "word": "лотерея детская", "hint": "билет", "special": "настольная ферма детская" }
  ],
  "technology_and_tools": [
    { "word": "компьютер", "hint": "мышь", "special": "ноутбук" },
    { "word": "ноутбук", "hint": "портативный", "special": "компьютер" },
    { "word": "планшет", "hint": "сенсор", "special": "смартфон" },
    { "word": "смартфон", "hint": "звонить", "special": "планшет" },
    { "word": "клавиатура", "hint": "печатать", "special": "мышь" },
    { "word": "мышь", "hint": "клик", "special": "клавиатура" },
    { "word": "монитор", "hint": "экран", "special": "телевизор" },
    { "word": "принтер", "hint": "бумага", "special": "сканер" },
    { "word": "сканер", "hint": "копировать", "special": "принтер" },
    { "word": "веб-камера", "hint": "снимать", "special": "фотоаппарат" },
    { "word": "фотоаппарат", "hint": "снимок", "special": "веб-камера" },
    { "word": "гарнитура", "hint": "звук", "special": "колонки" },
    { "word": "колонки", "hint": "музыка", "special": "гарнитура" },
    { "word": "наушники", "hint": "слушать", "special": "гарнитура" },
    { "word": "роутер", "hint": "интернет", "special": "модем" },
    { "word": "модем", "hint": "сеть", "special": "роутер" },
    { "word": "смарт-часы", "hint": "время", "special": "фитнес-браслет" },
    { "word": "фитнес-браслет", "hint": "шаги", "special": "смарт-часы" },
    { "word": "пауэрбанк", "hint": "заряд", "special": "аккумулятор" },
    { "word": "аккумулятор", "hint": "батарея", "special": "пауэрбанк" },
    { "word": "проектор", "hint": "экран", "special": "монитор" },
    { "word": "дрон", "hint": "летать", "special": "самолёт игрушечный" },
    { "word": "самолёт игрушечный", "hint": "играть", "special": "дрон" },
    { "word": "робот", "hint": "двигаться", "special": "автомат" },
    { "word": "автомат", "hint": "работает", "special": "робот" },
    { "word": "электроотвёртка", "hint": "винты", "special": "отвёртка" },
    { "word": "отвёртка", "hint": "закручивать", "special": "электроотвёртка" },
    { "word": "молоток", "hint": "гвозди", "special": "топор" },
    { "word": "топор", "hint": "рубить", "special": "молоток" },
    { "word": "пила", "hint": "резать", "special": "ножовка" },
    { "word": "ножовка", "hint": "дерево", "special": "пила" },
    { "word": "дрель", "hint": "сверлить", "special": "шуруповёрт" },
    { "word": "шуруповёрт", "hint": "винты", "special": "дрель" },
    { "word": "рулетка", "hint": "измерять", "special": "линейка" },
    { "word": "линейка", "hint": "сантиметры", "special": "рулетка" },
    { "word": "уровень", "hint": "горизонт", "special": "линейка" },
    { "word": "паяльник", "hint": "провод", "special": "термофен" },
    { "word": "термофен", "hint": "нагрев", "special": "паяльник" },
    { "word": "флешка", "hint": "память", "special": "карта памяти" },
    { "word": "карта памяти", "hint": "данные", "special": "флешка" },
    { "word": "жёсткий диск", "hint": "хранение", "special": "SSD" },
    { "word": "SSD", "hint": "скорость", "special": "жёсткий диск" },
    { "word": "сервер", "hint": "данные", "special": "компьютер" },
    { "word": "маркер", "hint": "пишет", "special": "ручка" },
    { "word": "ручка", "hint": "писать", "special": "маркер" },
    { "word": "карандаш", "hint": "рисовать", "special": "фломастер" },
    { "word": "фломастер", "hint": "цвет", "special": "карандаш" },
    { "word": "резак", "hint": "резать", "special": "нож" },
    { "word": "ножницы", "hint": "бумага", "special": "резак" },
    { "word": "степлер", "hint": "бумага", "special": "скрепки" },
    { "word": "скрепки", "hint": "держать", "special": "степлер" },
    { "word": "коробка для инструментов", "hint": "хранение", "special": "сумка" },
    { "word": "сумка для инструментов", "hint": "носить", "special": "коробка для инструментов" },
    { "word": "электропила", "hint": "резать", "special": "бензопила" },
    { "word": "бензопила", "hint": "дерево", "special": "электропила" },
    { "word": "сверлильный станок", "hint": "сверлить", "special": "дрель" },
    { "word": "лазерный уровень", "hint": "горизонт", "special": "уровень" },
    { "word": "микроскоп", "hint": "увеличить", "special": "лупа" },
    { "word": "лупа", "hint": "увеличение", "special": "микроскоп" },
    { "word": "телескоп", "hint": "звёзды", "special": "бинокль" },
    { "word": "бинокль", "hint": "наблюдать", "special": "телескоп" },
    { "word": "электрическая дрель", "hint": "сверлить", "special": "шуруповёрт" },
    { "word": "лазерная указка", "hint": "свет", "special": "фонарик" },
    { "word": "фонарик", "hint": "свет", "special": "лазерная указка" },
    { "word": "электробритва", "hint": "брить", "special": "ножницы" },
    { "word": "фен", "hint": "волосы", "special": "утюжок" },
    { "word": "утюжок", "hint": "гладить", "special": "фен" },
    { "word": "швейная машинка", "hint": "ткань", "special": "ручная игла" },
    { "word": "ручная игла", "hint": "шить", "special": "швейная машинка" },
    { "word": "электрический чайник", "hint": "вода", "special": "термопот" },
    { "word": "термопот", "hint": "горячая вода", "special": "электрический чайник" },
    { "word": "кухонный комбайн", "hint": "измельчать", "special": "блендер" },
    { "word": "блендер", "hint": "смузи", "special": "кухонный комбайн" },
    { "word": "миксер", "hint": "взбивать", "special": "блендер" },
    { "word": "электросамокат", "hint": "движение", "special": "велосипед" },
    { "word": "электровелосипед", "hint": "педали", "special": "электросамокат" },
    { "word": "робот-пылесос", "hint": "уборка", "special": "пылесос" },
    { "word": "пылесос", "hint": "чистота", "special": "робот-пылесос" },
    { "word": "умная колонка", "hint": "голос", "special": "динамик" },
    { "word": "динамик", "hint": "звук", "special": "умная колонка" },
    { "word": "дистанционный пульт", "hint": "управлять", "special": "кнопки" },
    { "word": "кнопки", "hint": "нажать", "special": "дистанционный пульт" },
    { "word": "электропила маленькая", "hint": "резать", "special": "ножовка" },
    { "word": "мультиметр", "hint": "ток", "special": "вольтметр" },
    { "word": "вольтметр", "hint": "напряжение", "special": "мультиметр" },
    { "word": "тестер батарей", "hint": "заряд", "special": "мультиметр" },
    { "word": "удлинитель", "hint": "розетка", "special": "сетевой фильтр" },
    { "word": "сетевой фильтр", "hint": "розетка", "special": "удлинитель" },
    { "word": "инструментальный набор", "hint": "ремонт", "special": "коробка инструментов" },
    { "word": "коробка инструментов", "hint": "хранение", "special": "инструментальный набор" },
    { "word": "электроинструмент", "hint": "работа", "special": "ручной инструмент" },
    { "word": "ручной инструмент", "hint": "работа", "special": "электроинструмент" },
    { "word": "геймпад", "hint": "игры", "special": "джойстик" },
    { "word": "джойстик", "hint": "кнопки", "special": "геймпад" },
    { "word": "сенсорный экран", "hint": "касание", "special": "планшет" },
    { "word": "калькулятор", "hint": "счёт", "special": "компьютер" },
    { "word": "электронная книга", "hint": "читать", "special": "планшет" },
    { "word": "паяльная станция", "hint": "пайка", "special": "паяльник" }
  ],
  "time_and_space": [
    { "word": "часы настенные", "hint": "время", "special": "будильник" },
    { "word": "будильник", "hint": "сигнал", "special": "часы настенные" },
    { "word": "песочные часы", "hint": "песок", "special": "таймер" },
    { "word": "таймер", "hint": "отсчёт", "special": "песочные часы" },
    { "word": "календарь настольный", "hint": "день", "special": "календарь настенный" },
    { "word": "календарь настенный", "hint": "месяц", "special": "календарь настольный" },
    { "word": "часы карманные", "hint": "механика", "special": "наручные часы" },
    { "word": "наручные часы", "hint": "рука", "special": "часы карманные" },
    { "word": "компас", "hint": "север", "special": "навигация" },
    { "word": "навигатор", "hint": "путь", "special": "компас" },
    { "word": "телескоп", "hint": "звёзды", "special": "бинокль" },
    { "word": "бинокль", "hint": "наблюдать", "special": "телескоп" },
    { "word": "астролябия", "hint": "звёзды", "special": "телескоп" },
    { "word": "космический корабль", "hint": "полет", "special": "шаттл" },
    { "word": "шаттл", "hint": "орбита", "special": "космический корабль" },
    { "word": "ракета", "hint": "запуск", "special": "шаттл" },
    { "word": "луна", "hint": "ночь", "special": "звезда" },
    { "word": "звезда", "hint": "свет", "special": "луна" },
    { "word": "планета", "hint": "космос", "special": "луна" },
    { "word": "солнечная система", "hint": "планеты", "special": "галактика" },
    { "word": "галактика", "hint": "млечный путь", "special": "солнечная система" },
    { "word": "астероид", "hint": "камень", "special": "комета" },
    { "word": "комета", "hint": "хвост", "special": "астероид" },
    { "word": "метеорит", "hint": "падение", "special": "астероид" },
    { "word": "орбита планеты", "hint": "круг", "special": "трасса спутника" },
    { "word": "трасса спутника", "hint": "полёт", "special": "орбита планеты" },
    { "word": "космическая станция", "hint": "работа", "special": "спутник" },
    { "word": "спутник", "hint": "орбита", "special": "космическая станция" },
    { "word": "солнечные часы", "hint": "тень", "special": "песочные часы" },
    { "word": "астрономическая обсерватория", "hint": "звёзды", "special": "планетарий" },
    { "word": "планетарий", "hint": "космос", "special": "астрономическая обсерватория" },
    { "word": "космонавт", "hint": "полет", "special": "астронавт" },
    { "word": "астронавт", "hint": "космос", "special": "космонавт" },
    { "word": "луноход", "hint": "марс", "special": "марсоход" },
    { "word": "марсоход", "hint": "марс", "special": "луноход" },
    { "word": "солнце", "hint": "день", "special": "луна" },
    { "word": "ночное небо", "hint": "темнота", "special": "дневное небо" },
    { "word": "дневное небо", "hint": "свет", "special": "ночное небо" },
    { "word": "млечный путь", "hint": "галактика", "special": "звёздное скопление" },
    { "word": "звёздное скопление", "hint": "множество", "special": "млечный путь" },
    { "word": "черная дыра", "hint": "гравитация", "special": "квазары" },
    { "word": "квазары", "hint": "энергия", "special": "черная дыра" },
    { "word": "астрология", "hint": "знаки", "special": "астрономия" },
    { "word": "астрономия", "hint": "звёзды", "special": "астрология" },
    { "word": "телепортация", "hint": "перемещение", "special": "полёт" },
    { "word": "полёт", "hint": "воздух", "special": "телепортация" },
    { "word": "космическая миссия", "hint": "полет", "special": "исследование" },
    { "word": "исследование космоса", "hint": "открытия", "special": "космическая миссия" },
    { "word": "лунная база", "hint": "луна", "special": "марсианская база" },
    { "word": "марсианская база", "hint": "марс", "special": "лунная база" },
    { "word": "звёздная карта", "hint": "навигация", "special": "карта созвездий" },
    { "word": "карта созвездий", "hint": "звёзды", "special": "звёздная карта" },
    { "word": "космодром", "hint": "ракета", "special": "аэродром" },
    { "word": "аэродром", "hint": "самолёт", "special": "космодром" },
    { "word": "метеостанция", "hint": "погода", "special": "обсерватория" },
    { "word": "обсерватория", "hint": "звёзды", "special": "метеостанция" },
    { "word": "астероидный пояс", "hint": "камни", "special": "планетарная орбита" },
    { "word": "планетарная орбита", "hint": "круг", "special": "астероидный пояс" },
    { "word": "солнечная орбита", "hint": "звезда", "special": "лунная орбита" },
    { "word": "лунная орбита", "hint": "луна", "special": "солнечная орбита" },
    { "word": "звёздный путь", "hint": "навигация", "special": "космический маршрут" },
    { "word": "космический маршрут", "hint": "полет", "special": "звёздный путь" },
    { "word": "межзвёздное пространство", "hint": "пустота", "special": "космос" },
    { "word": "космическая пустота", "hint": "ничто", "special": "межзвёздное пространство" },
    { "word": "орбитальная станция", "hint": "космос", "special": "космическая станция" },
    { "word": "звёздный час", "hint": "время", "special": "полночь" },
    { "word": "полночь", "hint": "темно", "special": "звёздный час" },
    { "word": "солнечный день", "hint": "свет", "special": "день" },
    { "word": "ночная тьма", "hint": "темнота", "special": "ночь" },
    { "word": "космическая экспедиция", "hint": "путешествие", "special": "экспедиция" },
    { "word": "внеземной объект", "hint": "небо", "special": "астероид" },
    { "word": "звёздная система", "hint": "планеты", "special": "галактика" },
    { "word": "черезвычайное время", "hint": "событие", "special": "чрезвычайная ситуация" },
    { "word": "временная зона", "hint": "часы", "special": "часовой пояс" },
    { "word": "часовой пояс", "hint": "время", "special": "временная зона" },
    { "word": "календарная дата", "hint": "день", "special": "событие" },
    { "word": "событие во времени", "hint": "момент", "special": "календарная дата" },
    { "word": "астрономический час", "hint": "звёзды", "special": "звёздное время" },
    { "word": "звёздное время", "hint": "планеты", "special": "астрономический час" },
    { "word": "временная метка", "hint": "момент", "special": "отсчёт" },
    { "word": "отсчёт времени", "hint": "секунды", "special": "временная метка" },
    { "word": "космическая орбита", "hint": "путь", "special": "планетарная орбита" },
    { "word": "планетарная система", "hint": "планеты", "special": "солнечная система" }
  ],
  "colors_and_shapes": [
    { "word": "красный круг", "hint": "круг", "special": "синий круг" },
    { "word": "синий квадрат", "hint": "квадрат", "special": "зелёный квадрат" },
    { "word": "зелёный треугольник", "hint": "треугольник", "special": "жёлтый треугольник" },
    { "word": "жёлтый овал", "hint": "овал", "special": "оранжевый овал" },
    { "word": "оранжевый прямоугольник", "hint": "прямоугольник", "special": "фиолетовый прямоугольник" },
    { "word": "фиолетовый ромб", "hint": "ромб", "special": "розовый ромб" },
    { "word": "розовый сердце", "hint": "сердце", "special": "красное сердце" },
    { "word": "чёрный квадрат", "hint": "квадрат", "special": "серый квадрат" },
    { "word": "белый круг", "hint": "круг", "special": "серый круг" },
    { "word": "серый треугольник", "hint": "треугольник", "special": "чёрный треугольник" },
    { "word": "голубой овал", "hint": "овал", "special": "синий овал" },
    { "word": "коричневый прямоугольник", "hint": "прямоугольник", "special": "бежевый прямоугольник" },
    { "word": "золотой ромб", "hint": "ромб", "special": "серебряный ромб" },
    { "word": "серебряное сердце", "hint": "сердце", "special": "золотое сердце" },
    { "word": "бирюзовый круг", "hint": "круг", "special": "голубой круг" },
    { "word": "лимонный треугольник", "hint": "треугольник", "special": "жёлтый треугольник" },
    { "word": "малиновый квадрат", "hint": "квадрат", "special": "розовый квадрат" },
    { "word": "лаймовый овал", "hint": "овал", "special": "зелёный овал" },
    { "word": "пурпурный прямоугольник", "hint": "прямоугольник", "special": "фиолетовый прямоугольник" },
    { "word": "бежевый ромб", "hint": "ромб", "special": "коричневый ромб" },
    { "word": "сиреневое сердце", "hint": "сердце", "special": "розовое сердце" },
    { "word": "чёрный овал", "hint": "овал", "special": "серый овал" },
    { "word": "белый прямоугольник", "hint": "прямоугольник", "special": "серый прямоугольник" },
    { "word": "серый круг", "hint": "круг", "special": "чёрный круг" },
    { "word": "голубой квадрат", "hint": "квадрат", "special": "бирюзовый квадрат" },
    { "word": "коричневый треугольник", "hint": "треугольник", "special": "бежевый треугольник" },
    { "word": "золотой круг", "hint": "круг", "special": "желтый круг" },
    { "word": "серебряный квадрат", "hint": "квадрат", "special": "серый квадрат" },
    { "word": "розовый овал", "hint": "овал", "special": "малиновый овал" },
    { "word": "фиолетовый треугольник", "hint": "треугольник", "special": "пурпурный треугольник" },
    { "word": "красное сердце", "hint": "сердце", "special": "розовое сердце" },
    { "word": "синий круг", "hint": "круг", "special": "голубой круг" },
    { "word": "зелёный квадрат", "hint": "квадрат", "special": "лаймовый квадрат" },
    { "word": "жёлтый ромб", "hint": "ромб", "special": "лимонный ромб" },
    { "word": "оранжевое сердце", "hint": "сердце", "special": "розовое сердце" },
    { "word": "бирюзовый прямоугольник", "hint": "прямоугольник", "special": "голубой прямоугольник" },
    { "word": "малиновый круг", "hint": "круг", "special": "розовый круг" },
    { "word": "пурпурный квадрат", "hint": "квадрат", "special": "фиолетовый квадрат" },
    { "word": "сиреневый овал", "hint": "овал", "special": "розовый овал" },
    { "word": "чёрный ромб", "hint": "ромб", "special": "серый ромб" },
    { "word": "белое сердце", "hint": "сердце", "special": "серебряное сердце" },
    { "word": "серый овал", "hint": "овал", "special": "чёрный овал" },
    { "word": "голубой треугольник", "hint": "треугольник", "special": "бирюзовый треугольник" },
    { "word": "коричневый круг", "hint": "круг", "special": "бежевый круг" },
    { "word": "золотой квадрат", "hint": "квадрат", "special": "желтый квадрат" },
    { "word": "серебряный ромб", "hint": "ромб", "special": "серый ромб" },
    { "word": "розовое сердце", "hint": "сердце", "special": "красное сердце" },
    { "word": "фиолетовый овал", "hint": "овал", "special": "пурпурный овал" },
    { "word": "красный треугольник", "hint": "треугольник", "special": "малиновый треугольник" },
    { "word": "синий прямоугольник", "hint": "прямоугольник", "special": "голубой прямоугольник" },
    { "word": "зелёный овал", "hint": "овал", "special": "лаймовый овал" },
    { "word": "жёлтый круг", "hint": "круг", "special": "лимонный круг" },
    { "word": "оранжевый квадрат", "hint": "квадрат", "special": "помаранчевый квадрат" },
    { "word": "фиолетовый ромб", "hint": "ромб", "special": "пурпурный ромб" },
    { "word": "розовый треугольник", "hint": "треугольник", "special": "малиновый треугольник" },
    { "word": "чёрное сердце", "hint": "сердце", "special": "серый сердце" },
    { "word": "белый прямоугольник", "hint": "прямоугольник", "special": "серый прямоугольник" },
    { "word": "серый квадрат", "hint": "квадрат", "special": "чёрный квадрат" },
    { "word": "голубой круг", "hint": "круг", "special": "бирюзовый круг" },
    { "word": "коричневый треугольник", "hint": "треугольник", "special": "бежевый треугольник" },
    { "word": "золотой овал", "hint": "овал", "special": "жёлтый овал" },
    { "word": "серебряный квадрат", "hint": "квадрат", "special": "серый квадрат" },
    { "word": "розовое сердце", "hint": "сердце", "special": "красное сердце" },
    { "word": "фиолетовый треугольник", "hint": "треугольник", "special": "пурпурный треугольник" },
    { "word": "красный квадрат", "hint": "квадрат", "special": "малиновый квадрат" },
    { "word": "синий ромб", "hint": "ромб", "special": "голубой ромб" },
    { "word": "зелёный овал", "hint": "овал", "special": "лаймовый овал" },
    { "word": "жёлтый треугольник", "hint": "треугольник", "special": "лимонный треугольник" },
    { "word": "оранжевое сердце", "hint": "сердце", "special": "розовое сердце" },
    { "word": "бирюзовый прямоугольник", "hint": "прямоугольник", "special": "голубой прямоугольник" },
    { "word": "малиновый круг", "hint": "круг", "special": "розовый круг" },
    { "word": "пурпурный квадрат", "hint": "квадрат", "special": "фиолетовый квадрат" },
    { "word": "сиреневый овал", "hint": "овал", "special": "розовый овал" },
    { "word": "чёрный ромб", "hint": "ромб", "special": "серый ромб" },
    { "word": "белое сердце", "hint": "сердце", "special": "серебряное сердце" },
    { "word": "серый овал", "hint": "овал", "special": "чёрный овал" },
    { "word": "голубой треугольник", "hint": "треугольник", "special": "бирюзовый треугольник" },
    { "word": "коричневый круг", "hint": "круг", "special": "бежевый круг" },
    { "word": "золотой квадрат", "hint": "квадрат", "special": "желтый квадрат" },
    { "word": "серебряный ромб", "hint": "ромб", "special": "серый ромб" },
    { "word": "розовое сердце", "hint": "сердце", "special": "красное сердце" },
    { "word": "фиолетовый овал", "hint": "овал", "special": "пурпурный овал" },
    { "word": "красный треугольник", "hint": "треугольник", "special": "малиновый треугольник" }
  ],
  "feelings_and_actions": [
    { "word": "радостный смех", "hint": "улыбка", "special": "весёлый смех" },
    { "word": "грустные слёзы", "hint": "печаль", "special": "тоскливые слёзы" },
    { "word": "злость", "hint": "ярость", "special": "раздражение" },
    { "word": "удивление", "hint": "шок", "special": "изумление" },
    { "word": "страх", "hint": "опасность", "special": "тревога" },
    { "word": "смелость", "hint": "храбрость", "special": "отвага" },
    { "word": "любовь", "hint": "сердце", "special": "привязанность" },
    { "word": "дружба", "hint": "товарищ", "special": "приятельство" },
    { "word": "играть в мяч", "hint": "спорт", "special": "бросать мяч" },
    { "word": "бегать", "hint": "движение", "special": "спринт" },
    { "word": "прыгать", "hint": "вверх", "special": "скакать" },
    { "word": "плавать", "hint": "вода", "special": "купаться" },
    { "word": "танцевать", "hint": "музыка", "special": "плясать" },
    { "word": "петь", "hint": "голос", "special": "напевать" },
    { "word": "рисовать", "hint": "краски", "special": "клеить" },
    { "word": "строить", "hint": "дом", "special": "создавать" },
    { "word": "готовить еду", "hint": "кухня", "special": "печь" },
    { "word": "читать книгу", "hint": "текст", "special": "листать" },
    { "word": "писать письмо", "hint": "ручка", "special": "записывать" },
    { "word": "думать", "hint": "мозг", "special": "размышлять" },
    { "word": "мечтать", "hint": "воображение", "special": "фантазировать" },
    { "word": "улыбаться", "hint": "губы", "special": "смеяться" },
    { "word": "плакать", "hint": "грусть", "special": "рыдать" },
    { "word": "обнимать", "hint": "тело", "special": "прижимать" },
    { "word": "целовать", "hint": "губы", "special": "прикасаться" },
    { "word": "шутить", "hint": "смех", "special": "разыгрывать" },
    { "word": "играть в прятки", "hint": "смешно", "special": "искать" },
    { "word": "кататься на велосипеде", "hint": "колёса", "special": "ездить" },
    { "word": "кататься на роликах", "hint": "скорость", "special": "скользить" },
    { "word": "кататься на коньках", "hint": "лед", "special": "скользить" },
    { "word": "бросать мяч", "hint": "рука", "special": "кидать" },
    { "word": "ловить мяч", "hint": "рука", "special": "поймать" },
    { "word": "качаться на качелях", "hint": "вверх", "special": "гнуться" },
    { "word": "кататься на санках", "hint": "снег", "special": "скользить" },
    { "word": "играть в песочнице", "hint": "песок", "special": "строить замки" },
    { "word": "искать", "hint": "найти", "special": "обнаруживать" },
    { "word": "находить", "hint": "радость", "special": "обнаруживать" },
    { "word": "улыбка", "hint": "губы", "special": "смех" },
    { "word": "смеяться", "hint": "звук", "special": "улыбка" },
    { "word": "спать", "hint": "сон", "special": "дремать" },
    { "word": "дремать", "hint": "коротко", "special": "спать" },
    { "word": "ходить", "hint": "ноги", "special": "гулять" },
    { "word": "гулять", "hint": "улица", "special": "ходить" },
    { "word": "бросать", "hint": "рука", "special": "кидать" },
    { "word": "кидать", "hint": "мяч", "special": "бросать" },
    { "word": "ловить", "hint": "рука", "special": "поймать" },
    { "word": "поймать", "hint": "мяч", "special": "ловить" },
    { "word": "играть", "hint": "развлечение", "special": "развлекаться" },
    { "word": "развлекаться", "hint": "весело", "special": "играть" },
    { "word": "кричать", "hint": "голос", "special": "выкрикивать" },
    { "word": "выкрикивать", "hint": "громко", "special": "кричать" },
    { "word": "шуметь", "hint": "звук", "special": "громко" },
    { "word": "тихо", "hint": "звук", "special": "спокойно" },
    { "word": "запрыгивать", "hint": "вверх", "special": "прыгать" },
    { "word": "прыгать", "hint": "вверх", "special": "скакать" },
    { "word": "катиться", "hint": "движение", "special": "скатываться" },
    { "word": "скатываться", "hint": "угол", "special": "катиться" },
    { "word": "бить", "hint": "удар", "special": "колотить" },
    { "word": "колотить", "hint": "удар", "special": "бить" },
    { "word": "рисовать карандашом", "hint": "рисунок", "special": "рисовать красками" },
    { "word": "рисовать красками", "hint": "цвет", "special": "рисовать карандашом" },
    { "word": "петь песню", "hint": "голос", "special": "напевать" },
    { "word": "напевать", "hint": "тихо", "special": "петь песню" },
    { "word": "писать рассказ", "hint": "текст", "special": "рисовать историю" },
    { "word": "рисовать историю", "hint": "картинки", "special": "писать рассказ" },
    { "word": "обнимать друга", "hint": "тепло", "special": "прижимать" },
    { "word": "прижимать", "hint": "близко", "special": "обнимать" },
    { "word": "улыбаться другу", "hint": "дружба", "special": "смеяться" },
    { "word": "смеяться вместе", "hint": "весело", "special": "улыбаться" },
    { "word": "дружить", "hint": "отношения", "special": "играть вместе" },
    { "word": "играть вместе", "hint": "развлечение", "special": "дружить" },
    { "word": "соревноваться", "hint": "конкурс", "special": "состязаться" },
    { "word": "состязаться", "hint": "игра", "special": "соревноваться" },
    { "word": "прощать", "hint": "ошибка", "special": "забывать" },
    { "word": "забывать", "hint": "время", "special": "прощать" },
    { "word": "сожалеть", "hint": "печаль", "special": "огорчаться" },
    { "word": "огорчаться", "hint": "грусть", "special": "сожалеть" },
    { "word": "радоваться", "hint": "счастье", "special": "веселиться" },
    { "word": "веселиться", "hint": "развлечение", "special": "радоваться" },
    { "word": "пугаться", "hint": "страх", "special": "бояться" },
    { "word": "бояться", "hint": "опасность", "special": "пугаться" },
    { "word": "обижаться", "hint": "чувство", "special": "злиться" },
    { "word": "злиться", "hint": "ярость", "special": "обижаться" }
  ]
}
